[
  {
    "quiz": 1685955518802,
    "user": 1685438248739,
    "bonnesReponses": [
      4,
      3,
      1
    ],
    "mauvaisesReponses": [
      2,
      2,
      0
    ],
    "times": 3,
    "timerMoyen": 10.5,
    "nbQuit": 1,
    "id": 1686926544937
  },
  {
    "quiz": 1685955518802,
    "user": 1685438248743,
    "bonnesReponses": [
      0,
      0,
      0
    ],
    "mauvaisesReponses": [
      0,
      0,
      0
    ],
    "times": 0,
    "timerMoyen": 0,
    "nbQuit": 0,
    "id": 1686926617127
  }
]